{
    "Player":
    {
        "Character": "@",
        "Name": "Player",
        
        "Hp": 20,
        "MaxHp": 20,

        "Weapon":
        {
            "Name": "Dagger",
            "Attack": 3
        },
        "Armor":
        {
            "Name": "Leather Armor",
            "Defence": 4
        },

        "Inventory":
        [
            {
                "Name": "Rabbit's Foot",
                "Value": 2
            }
        ]
    },

    "Levels":
    {
        "The Crossroads" : {
            "Name": "The Crossroads",
            "SpawnPosition": { "X": 2, "Y": 3 },
            "SurroundingLevels": ["The River", "The Bridge", null, "The Forest"],
            "Map":
            [
                "_____",
                "__P0_",
                "0____",
                "_____",
                "___0_"
            ],
            "Actors":
            {
                "P":
                {
                    "Name": "Old Sign Post",
                    "Hp": 3,
                    "MaxHp": 3,
                    "Character": "P",

                    "Encounter":
                    {
                        "Message": "You see an old sign post that reads:\n\nNORTH - River\nEAST - Bridge\nSOUTH - Dungeon\nWEST - Forest\n\nAdventure at your own risk..."
                    }
                },

                "0":
                {
                    "Name": "Oak Tree",
                    "Hp": 100,
                    "MaxHp": 100,
                    "Character": "0",

                    "Encounter":
                    {
                        "Message": "You see a strong oak tree ground from the ground."
                    }
                }
            }
        },
        "The River" : {
            "Name": "The River",
            "SpawnPosition": { "X": 3, "Y": 7 },
            "SurroundingLevels": [null, null, "The Crossroads", null],
            "Map":
            [
                "...____",
                "....___",
                "__.....",
                "___....",
                "_______",
                "_______",
                "_______",
                "_______"
            ],
            
            "Actors":
            {
                ".":
                {
                    "Name": "River Water",
                    "Hp": 1000,
                    "MaxHp": 1000,
                    "character": ".",

                    "Encounter":
                    {
                        "Message": "You see a running stream, will you drink the water?",
                        "Options":
                        [
                            {
                                "OptionName": "Drink Water",
                                "Message": "You feel healed and rested!",
                                "Effect": 
                                {
                                    "Target": "Player",
                                    "Function": "ModifyHp",
                                    "Amount": 10
                                }
                            }
                        ]
                    }
                }
            }
        },
        "The Bridge" : {
            "Name": "The Bridge",
            "SpawnPosition": { "X": 0, "Y": 4 },
            "SurroundingLevels": [null, null, null, "The Crossroads"],
            "Map":
            [
                ".__0_0___",
                "...____0_",
                "_....0___",
                "_0_..____",
                "___==____",
                "___..__0_"

            ]
        },
        "The Forest" : {
            "Name": "The Forest",
            "SpawnPosition": { "X": 8, "Y": 3 },
            "SurroundingLevels": [null, "The Crossroads", null, null],
            "Map":
            [
                "_0___0_0_",
                "---_0____",
                "C_|___0__",
                "CH_______",
                "C_|__0___",
                "---____0_"

            ]
        }
    }
}